shopcloud_eventbus/__init__.py
shopcloud_eventbus/__main__.py
shopcloud_eventbus/cli.py
shopcloud_eventbus/events.py
shopcloud_eventbus/exceptions.py
shopcloud_eventbus/file_content.py
shopcloud_eventbus/helpers.py
shopcloud_eventbus/test_cli.py
shopcloud_eventbus-1.5.0.data/scripts/eventbus
shopcloud_eventbus-1.5.0.dist-info/LICENSE
shopcloud_eventbus-1.5.0.dist-info/METADATA
shopcloud_eventbus-1.5.0.dist-info/WHEEL
shopcloud_eventbus-1.5.0.dist-info/top_level.txt
shopcloud_eventbus-1.5.0.dist-info/RECORD
