Metadata-Version: 2.1
Name: shopcloud-eventbus
Version: 1.5.0
Summary: CLI tool for the Shopcloud EventBus
Home-page: https://github.com/Talk-Point/shopcloud-eventbus
Author: Konstantin Stoldt
Author-email: konstantin.stoldt@talk-point.de
License: MIT
Keywords: CLI
License-File: LICENSE
Requires-Dist: pyyaml
Requires-Dist: shopcloud-secrethub >=2.12.0
